_version.py
neutronics_material_maker/__init__.py
neutronics_material_maker/material.py
neutronics_material_maker/utils.py
neutronics_material_maker/data/__init__.py
neutronics_material_maker/data/breeder_materials.json
neutronics_material_maker/data/breeder_materials_with_crystal_structure.json
neutronics_material_maker/data/coolant_materials.json
neutronics_material_maker/data/insulators.json
neutronics_material_maker/data/magnet_materials.json
neutronics_material_maker/data/moderators.json
neutronics_material_maker/data/multiplier_and_breeder_materials.json
neutronics_material_maker/data/multiplier_materials.json
neutronics_material_maker/data/plasma_material.json
neutronics_material_maker/data/pnnl_materials.json
neutronics_material_maker/data/scintillators.json
neutronics_material_maker/data/structural_materials.json
neutronics_material_maker-1.2.1.dist-info/LICENSE.txt
neutronics_material_maker-1.2.1.dist-info/METADATA
neutronics_material_maker-1.2.1.dist-info/WHEEL
neutronics_material_maker-1.2.1.dist-info/top_level.txt
neutronics_material_maker-1.2.1.dist-info/RECORD
