Metadata-Version: 2.1
Name: neutronics_material_maker
Version: 1.2.1
Summary: A tool for making reproducible materials and standardizing use across several neutronics codes
Author-email: Jonathan Shimwell <mail@jshimwell.com>
License: MIT License
Project-URL: Homepage, https://github.com/fusion-energy/neutronics_material_maker
Project-URL: Bug Tracker, https://github.com/fusion-energy/neutronics_material_maker/issues
Keywords: material,library,database,serpent,mcnp,openmc,fispact
Classifier: Programming Language :: Python :: 3
Classifier: License :: OSI Approved :: MIT License
Classifier: Operating System :: OS Independent
Requires-Python: >=3.8
License-File: LICENSE.txt
Requires-Dist: asteval>=0.9.20
Provides-Extra: density
Requires-Dist: coolprop; extra == "density"
Provides-Extra: docs
Requires-Dist: sphinx; extra == "docs"
Requires-Dist: sphinx-autodoc-typehints; extra == "docs"
Provides-Extra: tests
Requires-Dist: pytest; extra == "tests"
Requires-Dist: pytest-cov; extra == "tests"
